duck_chat/__init__.py
duck_chat/__main__.py
duck_chat/api.py
duck_chat/cli.py
duck_chat/exceptions.py
duck_chat/models.py
duck_chat/py.typed
duck_chat-1.3.2.dist-info/METADATA
duck_chat-1.3.2.dist-info/WHEEL
duck_chat-1.3.2.dist-info/entry_points.txt
duck_chat-1.3.2.dist-info/licenses/LICENSE
duck_chat-1.3.2.dist-info/RECORD
