Metadata-Version: 2.3
Name: duck_chat
Version: 1.3.2
Summary: DuckDuckGo Chat AI client
Project-URL: Homepage, https://github.com/mrgick/duckduckgo-chat-ai
Project-URL: Issues, https://github.com/mrgick/duckduckgo-chat-ai/issues
Author-email: MrGick <mrgickcool@gmail.com>
License: MIT License
License-File: LICENSE
Classifier: Intended Audience :: Developers
Classifier: Intended Audience :: Information Technology
Classifier: Intended Audience :: System Administrators
Classifier: Operating System :: OS Independent
Classifier: Programming Language :: Python
Classifier: Programming Language :: Python :: 3
Classifier: Programming Language :: Python :: 3 :: Only
Classifier: Programming Language :: Python :: 3.11
Classifier: Programming Language :: Python :: 3.12
Classifier: Topic :: Internet
Classifier: Topic :: Internet :: WWW/HTTP
Classifier: Topic :: Internet :: WWW/HTTP :: HTTP Servers
Classifier: Topic :: Software Development
Classifier: Topic :: Software Development :: Libraries
Classifier: Topic :: Software Development :: Libraries :: Application Frameworks
Classifier: Topic :: Software Development :: Libraries :: Python Modules
Classifier: Typing :: Typed
Requires-Python: >=3.11
Requires-Dist: aiohttp[speedups]>=3.9.5
Requires-Dist: fake-useragent>=1.5.1
Requires-Dist: msgspec>=0.18.6
Requires-Dist: rich>=13.7.1
Provides-Extra: dev
Requires-Dist: black>=24.4.2; extra == 'dev'
Requires-Dist: isort>=5.13.2; extra == 'dev'
Requires-Dist: mypy>=1.11.1; extra == 'dev'
Requires-Dist: ruff>=0.5.1; extra == 'dev'
